{"commitInfo":{"timestamp":1782518507417,"userId":"70464571750447","userName":"lleandrogon2004@gmail.com","operation":"WRITE","operationParameters":{"mode":"Overwrite","statsOnLoad":false,"partitionBy":"[]","canMergeSchema":true},"notebook":{"notebookId":"1354590108941865"},"queryHistoryStatementId":"9ef8e830-aa1d-4c51-8dbe-5c3443eb7804","clusterId":"0626-224821-xt77isci-v2n","isolationLevel":"WriteSerializable","isBlindAppend":false,"operationMetrics":{"numFiles":"1","numRemovedFiles":"0","numRemovedBytes":"0","numDeletionVectorsRemoved":"0","numOutputRows":"1294","numOutputBytes":"116347"},"tags":{"noRowsCopied":"true","restoresDeletedRows":"false"},"engineInfo":"Databricks-Runtime/18.2.x-aarch64-photon-scala2.13","txnId":"31082e55-236b-4246-accf-a3c4744ad8e6"}}
{"metaData":{"id":"f1bb1b98-52e4-40fc-ab73-6bfa74ce9c47","format":{"provider":"parquet","options":{}},"schemaString":"{\"type\":\"struct\",\"fields\":[{\"name\":\"country\",\"type\":\"string\",\"nullable\":true,\"metadata\":{}},{\"name\":\"region\",\"type\":\"string\",\"nullable\":true,\"metadata\":{}},{\"name\":\"income_group\",\"type\":\"string\",\"nullable\":true,\"metadata\":{}},{\"name\":\"year\",\"type\":\"integer\",\"nullable\":true,\"metadata\":{}},{\"name\":\"population\",\"type\":\"integer\",\"nullable\":true,\"metadata\":{}},{\"name\":\"gdp_usd\",\"type\":\"double\",\"nullable\":true,\"metadata\":{}},{\"name\":\"total_electricity_generation_twh\",\"type\":\"double\",\"nullable\":true,\"metadata\":{}},{\"name\":\"electricity_demand_twh\",\"type\":\"double\",\"nullable\":true,\"metadata\":{}},{\"name\":\"solar_electricity_twh\",\"type\":\"double\",\"nullable\":true,\"metadata\":{}},{\"name\":\"wind_electricity_twh\",\"type\":\"double\",\"nullable\":true,\"metadata\":{}},{\"name\":\"renewables_electricity_twh\",\"type\":\"double\",\"nullable\":true,\"metadata\":{}},{\"name\":\"hydro_electricity_twh\",\"type\":\"double\",\"nullable\":true,\"metadata\":{}},{\"name\":\"nuclear_electricity_twh\",\"type\":\"double\",\"nullable\":true,\"metadata\":{}},{\"name\":\"fossil_electricity_twh\",\"type\":\"double\",\"nullable\":true,\"metadata\":{}},{\"name\":\"solar_share_pct\",\"type\":\"double\",\"nullable\":true,\"metadata\":{}},{\"name\":\"wind_share_pct\",\"type\":\"double\",\"nullable\":true,\"metadata\":{}},{\"name\":\"renewables_share_pct\",\"type\":\"double\",\"nullable\":true,\"metadata\":{}},{\"name\":\"fossil_share_pct\",\"type\":\"double\",\"nullable\":true,\"metadata\":{}},{\"name\":\"low_carbon_share_pct\",\"type\":\"double\",\"nullable\":true,\"metadata\":{}},{\"name\":\"carbon_intensity_gco2_kwh\",\"type\":\"double\",\"nullable\":true,\"metadata\":{}},{\"name\":\"co2_saved_solar_wind_mt\",\"type\":\"double\",\"nullable\":true,\"metadata\":{}},{\"name\":\"solar_yoy_growth_pct\",\"type\":\"double\",\"nullable\":true,\"metadata\":{}},{\"name\":\"wind_yoy_growth_pct\",\"type\":\"double\",\"nullable\":true,\"metadata\":{}},{\"name\":\"renewables_yoy_growth_pct\",\"type\":\"double\",\"nullable\":true,\"metadata\":{}},{\"name\":\"policy_milestone\",\"type\":\"string\",\"nullable\":true,\"metadata\":{}}]}","partitionColumns":[],"configuration":{"delta.enableDeletionVectors":"true"},"createdTime":1782518504017}}
{"protocol":{"minReaderVersion":3,"minWriterVersion":7,"readerFeatures":["deletionVectors"],"writerFeatures":["deletionVectors","appendOnly","invariants"]}}
{"add":{"path":"part-00000-9a3e7e36-395f-4d97-b387-d4d3fa6a7147.c000.snappy.parquet","partitionValues":{},"size":116347,"modificationTime":1782518507000,"dataChange":true,"stats":"{\"numRecords\":1294,\"minValues\":{\"country\":\"Algeria\",\"region\":\"Africa\",\"income_group\":\"High\",\"year\":2000,\"population\":1954713,\"gdp_usd\":7.1053965539E10,\"total_electricity_generation_twh\":15.94,\"electricity_demand_twh\":15.94,\"solar_electricity_twh\":0.0,\"wind_electricity_twh\":0.0,\"renewables_electricity_twh\":0.0,\"hydro_electricity_twh\":0.0,\"nuclear_electricity_twh\":0.0,\"fossil_electricity_twh\":0.41,\"solar_share_pct\":0.0,\"wind_share_pct\":0.0,\"renewables_share_pct\":0.0,\"fossil_share_pct\":0.288,\"low_carbon_share_pct\":0.0,\"carbon_intensity_gco2_kwh\":25.75,\"co2_saved_solar_wind_mt\":0.0,\"solar_yoy_growth_pct\":-94.0,\"wind_yoy_growth_pct\":-100.0,\"renewables_yoy_growth_pct\":-60.0,\"policy_milestone\":\"100% renewable electricity by 20\"},\"maxValues\":{\"country\":\"Vietnam\",\"region\":\"South America\",\"income_group\":\"Upper-middle\",\"year\":2025,\"population\":1463865527,\"gdp_usd\":2.6966016991166E13,\"total_electricity_generation_twh\":10583.36,\"electricity_demand_twh\":10563.9,\"solar_electricity_twh\":1174.96,\"wind_electricity_twh\":1135.44,\"renewables_electricity_twh\":3920.47,\"hydro_electricity_twh\":1397.06,\"nuclear_electricity_twh\":809.41,\"fossil_electricity_twh\":6237.2,\"solar_share_pct\":25.062,\"wind_share_pct\":29.366,\"renewables_share_pct\":99.712,\"fossil_share_pct\":100.0,\"low_carbon_share_pct\":99.712,\"carbon_intensity_gco2_kwh\":1150.48,\"co2_saved_solar_wind_mt\":1039.68,\"solar_yoy_growth_pct\":24000.0,\"wind_yoy_growth_pct\":7800.0,\"renewables_yoy_growth_pct\":1124.5,\"policy_milestone\":\"Singapore Green Plan 2030\"},\"nullCount\":{\"country\":0,\"region\":0,\"income_group\":0,\"year\":0,\"population\":0,\"gdp_usd\":144,\"total_electricity_generation_twh\":0,\"electricity_demand_twh\":0,\"solar_electricity_twh\":0,\"wind_electricity_twh\":32,\"renewables_electricity_twh\":0,\"hydro_electricity_twh\":76,\"nuclear_electricity_twh\":6,\"fossil_electricity_twh\":0,\"solar_share_pct\":0,\"wind_share_pct\":32,\"renewables_share_pct\":0,\"fossil_share_pct\":0,\"low_carbon_share_pct\":0,\"carbon_intensity_gco2_kwh\":0,\"co2_saved_solar_wind_mt\":0,\"solar_yoy_growth_pct\":458,\"wind_yoy_growth_pct\":358,\"renewables_yoy_growth_pct\":83,\"policy_milestone\":1235},\"tightBounds\":true}","tags":{"INSERTION_TIME":"1782518507000000","MIN_INSERTION_TIME":"1782518507000000","MAX_INSERTION_TIME":"1782518507000000","OPTIMIZE_TARGET_SIZE":"268435456"}}}
